curve/__init__.py
curve/curve.py
curve-0.1.0.dist-info/METADATA
curve-0.1.0.dist-info/WHEEL
curve-0.1.0.dist-info/top_level.txt
curve-0.1.0.dist-info/RECORD
