Metadata-Version: 2.2
Name: curve
Version: 0.1.0
Summary: A waveform manipulation and analysis library for Python
Home-page: https://bitbucket.org/jpcgt/curve
Author: Juan Pablo Caram
Author-email: jpcaram@gmail.com
Requires: matplotlib
Requires: numpy
Requires: scipy
Requires-Python: >=3.6
Requires-Dist: matplotlib
Requires-Dist: numpy
Requires-Dist: scipy
Dynamic: author
Dynamic: author-email
Dynamic: description
Dynamic: description-content-type
Dynamic: home-page
Dynamic: requires
Dynamic: requires-dist
Dynamic: requires-python
Dynamic: summary
